pyvasa/__init__.py
pyvasa/appliance_management.py
pyvasa/datastore.py
pyvasa/extension_management.py
pyvasa/product_capability.py
pyvasa/reports.py
pyvasa/storage_capability_profile.py
pyvasa/storage_systems.py
pyvasa/task.py
pyvasa/user_authentication.py
pyvasa-1.0.dist-info/LICENSE
pyvasa-1.0.dist-info/METADATA
pyvasa-1.0.dist-info/WHEEL
pyvasa-1.0.dist-info/top_level.txt
pyvasa-1.0.dist-info/RECORD
